{"transcript":"kontɾaˈβando","exists":true,"definitions":["Introducción o exportación de géneros prohibidos por las leyes.","Comercio o producción de mercancías prohibidas por las leyes a los particulares.","Mercancía prohibida o introducida fraudulentamente."],"examples":["El contrabando de tabaco.","Fue detenido por contrabando.","Mercancía de contrabando."],"lemma":"contrabando","lemmaPos":"noun","synonyms":["estraperlo","tráfico","clandestinidad","matute"],"number":"singular","pluralForm":"los contrabandos","gender":"masculine","source":"contrabando"}