{"transcript":"a.taˈkaɾ","exists":true,"definitions":["Acometer con ímpetu y violencia contra algo o alguien.","Emprender una acción contra algo o alguien.","Producir un efecto dañino o perjudicial sobre algo o alguien.","Abordar un tema o problema con decisión."],"examples":["El ejército decidió atacar al amanecer.","La enfermedad puede atacar el sistema inmunológico.","Vamos a atacar este problema desde varios frentes.","Los perros atacaron al intruso."],"lemma":"atacar","lemmaPos":"verb","synonyms":["agredir","embestir","asaltar","acometer"],"number":"singular","pastTenses":"atacó, ha atacado","tense":"present","source":"atacar"}