{"source":"tejido","number":"singular","lemma":"tejer","lemmaPos":"verb","definitions":["Acción y efecto de tejer.","Obra formada al tejer.","Cada uno de los materiales orgánicos con los que están formados los diferentes órganos de los seres vivos."],"examples":["El tejido de la bufanda es suave.","Se especializa en el tejido a mano.","El tejido muscular permite el movimiento."],"synonyms":["trama","malla","textura"],"transcript":"teˈxiðo","gender":"masculine","tense":"past","pastTenses":"he tejido, hube tejido"}