{"transcript":"ˈtjeso","source":"Tieso","definitions":["Que está rígido o duro.","Que no tiene flexibilidad.","Que está muerto.","Que tiene mucho dinero (coloquial).","Que está ebrio (coloquial)."],"examples":["El cadáver estaba tieso.","Se quedó tieso del susto.","Está tieso de la espalda.","Es un tieso, siempre paga él.","Después de unas copas, estaba tieso."],"lemma":"tieso","lemmaPos":"adjective","synonyms":["rígido","duro","inflexible","muerto","adinerado","borracho"],"number":"singular","gender":"masculine"}