{"transcript":"eksˈpwesto","exists":true,"definitions":["Participio pasado de exponer.","Que ha sido mostrado o exhibido públicamente.","Que está en una situación de riesgo o peligro.","Que ha sido presentado o explicado."],"examples":["El cuadro fue expuesto en la galería.","Se ha expuesto a un gran peligro.","El tema fue expuesto con claridad.","Los datos están expuestos en el informe."],"lemma":"exponer","lemmaPos":"verb","synonyms":["mostrar","exhibir","presentar","arriesgar"],"number":"singular","pastTenses":"expuse, he expuesto","tense":"past","gender":"masculine","source":"expuesto"}