{"transcript":"funˈdido","exists":true,"definitions":["Acción y efecto de fundir o fundirse.","Material que ha sido fundido y solidificado.","En cine y televisión, efecto de transición en el que una imagen se desvanece gradualmente mientras otra aparece."],"examples":["El fundido del metal requirió altas temperaturas.","La pieza de fundido era muy resistente.","Utilizaron un fundido encadenado para la siguiente escena."],"lemma":"fundir","lemmaPos":"verb","synonyms":["fusión","aleación","disolución"],"number":"singular","pluralForm":"los fundidos","gender":"masculine","source":"fundido"}