{"transcript":"ˈwelɡa","exists":true,"definitions":["Del verbo \"holgar\": Dicho de una cosa: Sobrar o ser inútil.","Del verbo \"holgar\": Dicho de una persona: Estar ociosa, no trabajar.","Del verbo \"holgar\": Dicho de una persona: Descansar, tomar un respiro."],"examples":["Huelga decir que no estoy de acuerdo.","Si no trabajas, huelga.","Después de tanto esfuerzo, huelga un poco."],"lemma":"holgar","lemmaPos":"verb","synonyms":["sobrar","ociar","descansar"],"number":"singular","tense":"present","pastTenses":"holgó, ha holgado","source":"huelga"}