{"transcript":"eŋ.ɡaˈɲan.do","exists":true,"definitions":["Acción de inducir a error o a creer algo que no es verdad.","Acción de ser infiel en una relación.","Acción de simular o fingir algo."],"examples":["Estaba engañando a su hermano con el juego.","La pareja se estaba engañando mutuamente.","El mago estaba engañando a la audiencia con su truco."],"lemma":"engañar","lemmaPos":"verb","synonyms":["defraudar","mentir","traicionar","falsear"],"number":"singular","pastTenses":"engañó, ha engañado","tense":"present","source":"engañando"}