{"transcript":"desˈtaka","exists":true,"definitions":["Sobresalir o ser más notable que otros.","Poner de relieve o hacer que algo sea más visible o importante.","Resaltar una cualidad o característica."],"examples":["Su talento destaca entre los demás.","La torre destaca en el horizonte.","El informe destaca la importancia del proyecto."],"lemma":"destacar","lemmaPos":"verb","synonyms":["sobresalir","resaltar","distinguir"],"number":"singular","tense":"present","pastTenses":"destacó, ha destacado","source":"destaca"}