{"source":"destruir","number":"singular","lemma":"destruir","lemmaPos":"verb","definitions":["Deshacer o arruinar una cosa material.","Acabar con algo inmaterial, como una ilusión o un argumento.","Causar gran daño o devastación."],"examples":["La explosión va a destruir el edificio.","Sus palabras pueden destruir la confianza.","El fuego amenaza con destruir el bosque."],"synonyms":["demoler","arrasar","aniquilar","derribar"],"transcript":"des.tɾuˈiɾ","tense":"present","pastTenses":"destruyó, ha destruido"}