{"transcript":"maˈɾaka","exists":true,"definitions":["Instrumento musical de percusión, consistente en un recipiente hueco con semillas o bolitas dentro, que se agita para producir sonido.","En algunos países, persona tonta o ingenua.","En algunos países, cabeza."],"examples":["El músico agitó la maraca al ritmo de la canción.","¡No seas maraca y presta atención!","Se golpeó la maraca al caer."],"lemma":"maraca","lemmaPos":"noun","synonyms":["sonajero","cabeza","tonto"],"number":"singular","pluralForm":"las maracas","gender":"feminine","source":"la maraca"}