{"transcript":"mo.toˈsje.ras","exists":true,"definitions":["Herramienta motorizada con una cadena dentada para cortar madera.","Máquina portátil con motor y sierra de cadena para talar árboles o cortar troncos."],"examples":["Las motosierras son peligrosas si no se usan correctamente.","Necesitamos varias motosierras para limpiar el bosque.","El ruido de las motosierras era ensordecedor."],"lemma":"motosierra","lemmaPos":"noun","synonyms":["sierra de cadena","sierra mecánica"],"number":"plural","pluralForm":"las motosierras","gender":"feminine","source":"motosierras"}