{"transcript":"el si.lo.fo.no","exists":true,"definitions":["Instrumento musical de percusión formado por una serie de láminas de madera, ordenadas horizontalmente según su tamaño y sonido, que se golpean con mazas para producir notas musicales.","Juguete musical que imita un xilófono, a menudo con láminas de colores."],"examples":["El niño toca el xilófono.","El xilófono tiene un sonido dulce.","Aprendí a tocar el xilófono en la escuela."],"lemma":"xilófono","lemmaPos":"noun","synonyms":["marimba","silófono"],"number":"singular","pluralForm":"los xilófonos","gender":"masculine","source":"el xilófono"}