{"transcript":"disfɾaˈθaɾ","exists":true,"definitions":["Articular o vestir a alguien para que no sea reconocido.","Desfigurar o encubrir el aspecto natural de algo.","Ocultar un sentimiento o intención."],"examples":["Disfrazar al niño de pirata.","Disfrazar la realidad con mentiras.","Disfrazar su tristeza con una sonrisa."],"lemma":"disfrazar","lemmaPos":"verb","synonyms":["enmascarar","ocultar","caracterizar","camuflar"],"number":"singular","pastTenses":"disfracé, he disfrazado","tense":"present","source":"disfrazar"}