{"transcript":"desˈplje.ɣe","exists":true,"definitions":["Acción y efecto de extender lo que estaba plegado.","Manifestación de una actividad o cualidad.","Distribución de tropas o medios en un lugar para una operación."],"examples":["El despliegue de las velas.","Un gran despliegue de recursos.","El despliegue militar en la frontera."],"lemma":"despliegue","lemmaPos":"noun","synonyms":["extensión","desarrollo","exhibición","colocación"],"number":"singular","pluralForm":"los despliegues","gender":"masculine","source":"el despliegue"}