{"transcript":"inauÉĄuÉūaËÎļjones","exists":true,"definitions":["Actos o ceremonias con los que se inicia oficialmente una actividad, un edificio, una exposiciÃģn, etc.","Celebraciones de la apertura de algo nuevo."],"examples":["Las inauguraciones de los museos siempre atraen a mucha gente.","Hubo varias inauguraciones de tiendas en el centro comercial.","Las inauguraciones de obras pÃšblicas son importantes para la comunidad."],"lemma":"inauguraciÃģn","lemmaPos":"noun","synonyms":["aperturas","estrenos","comienzos"],"number":"plural","pluralForm":"las inauguraciones","gender":"feminine","source":"inauguraciones"}