{"transcript":"suβiˈdon","exists":true,"definitions":["Aumento repentino e intenso de una sensación, sentimiento o estado físico.","Subida brusca de precio, valor o intensidad de algo.","Efecto eufórico producido por una droga o por la adrenalina."],"examples":["Me dio un subidón de adrenalina.","Vaya subidón de precios este mes.","Sintió un subidón de alegría al verlo."],"lemma":"subidón","lemmaPos":"noun","synonyms":["aumento","incremento","euforia","clímax"],"number":"singular","pluralForm":"los subidones","gender":"masculine","source":"subidón"}