{"transcript":"θeluˈlaɾ","exists":true,"definitions":["Dispositivo electrónico inalámbrico para acceder a la red de telefonía móvil.","Pequeño grupo de personas que actúan como unidad dentro de una organización mayor."],"examples":["Olvidé mi celular en casa.","Compré un celular nuevo.","La celular terrorista fue desmantelada."],"lemma":"celular","lemmaPos":"noun","synonyms":["móvil","teléfono","unidad","célula"],"number":"singular","pluralForm":"los celulares","gender":"masculine","source":"celular"}