{"transcript":"fɾustɾaˈsjon","exists":true,"definitions":["Sentimiento de decepción o desilusión causado por la imposibilidad de lograr un objetivo o satisfacer un deseo.","Acción o efecto de frustrar o frustrarse."],"examples":["La frustración era evidente en su rostro.","Experimentó una profunda frustración al no conseguir el ascenso.","Manejó su frustración con madurez."],"lemma":"frustración","lemmaPos":"noun","synonyms":["decepción","desilusión","desengaño","chasco"],"number":"singular","pluralForm":"las frustraciones","gender":"feminine","source":"frustración"}