{"transcript":"in.tɾo.βeɾˈtiɾ","exists":true,"definitions":["Dirigir la atención o el interés hacia el propio mundo interior.","Hacer que una persona se vuelva introvertida o se encierre en sí misma."],"examples":["Suele introvertir sus sentimientos.","La experiencia lo hizo introvertir.","Es importante no introvertir demasiado."],"lemma":"introvertir","lemmaPos":"verb","synonyms":["ensimismarse","retraerse","reflexionar"],"number":"singular","pastTenses":"introvertí, he introvertido","tense":"present","source":"introvertir"}