{"transcript":"ˈʝen.do.se","exists":true,"definitions":["Forma del gerundio del verbo ir, que indica la acción de marcharse o partir de un lugar, con el pronombre reflexivo 'se' adjunto.","Indica el acto de abandonar un sitio o situación, a menudo con un matiz de alejamiento o partida."],"examples":["Estaba yéndose cuando lo llamaron.","Se despidió y siguió yéndose por el camino.","Los niños estaban yéndose de la fiesta."],"lemma":"ir","lemmaPos":"verb","synonyms":["marchándose","partiendo","alejándose","saliendo"],"number":"singular","pastTenses":"se fue, se ha ido","tense":"present","source":"yéndose"}