{"transcript":"re.peˈtiɾ","exists":true,"definitions":["Decir o hacer de nuevo lo que ya se había dicho o hecho.","Volver a ocurrir o aparecer algo.","Hacer que un alumno curse de nuevo un año o asignatura por no haberla aprobado."],"examples":["Voy a repetir la pregunta para que quede claro.","La historia tiende a repetir los mismos errores.","Mi hijo tuvo que repetir el curso de matemáticas."],"lemma":"repetir","lemmaPos":"verb","synonyms":["reiterar","reproducir","duplicar","recapitular"],"number":"singular","pastTenses":"repetí, has repetido","tense":"present","source":"repetir"}