{"transcript":"a.paˈsjo.no","exists":true,"definitions":["Primera persona del singular del presente de indicativo del verbo apasionar.","Sentir una pasión intensa por algo o alguien.","Entusiasmarse o excitarse mucho por una actividad o interés."],"examples":["Me apasiono con la música clásica.","Cuando pinto, me apasiono y olvido el tiempo.","Me apasiono por los deportes extremos."],"lemma":"apasionar","lemmaPos":"verb","synonyms":["entusiasmar","enamorar","excitar","fascinar","cautivar"],"number":"singular","pastTenses":"apasioné, he apasionado","tense":"present","source":"apasiono"}