{"transcript":"pɾomeˈðjaɾ","exists":true,"definitions":["Calcular el valor medio de varias cantidades.","Llegar a un punto medio o intermedio de un tiempo o lugar.","Interceder o mediar entre dos o más partes."],"examples":["Debemos promediar los resultados.","Al promediar el mes, terminaremos.","Promediar entre los litigantes."],"lemma":"promediar","lemmaPos":"verb","synonyms":["mediar","equilibrar","interceder","centrar"],"number":"singular","pastTenses":"promedié, he promediado","tense":"present","source":"promediar"}