{"source":"descendiente","number":"singular","lemma":"descendiente","lemmaPos":"noun","definitions":["Persona que desciende de otra, de una familia, de una estirpe, especialmente si ha pasado mucho tiempo o hay varias generaciones.","Dicho de una cosa: Que procede de otra."],"examples":["Es descendiente de una noble familia.","Los descendientes de los inmigrantes.","Un descendiente directo del fundador.","El español es descendiente del latín."],"synonyms":["vástago","heredero","sucesor","progenie","hijo"],"transcript":"des.senˈdjen.te"}