{"transcript":"/ˈle.o/","source":"leo","definitions":["Yo leo (presente indicativo de leer): Percibir y comprender el significado de un texto escrito o impreso.","Yo leo (presente indicativo de leer): Decir en voz alta un texto escrito.","Yo leo (presente indicativo de leer): Estudiar o descifrar algo, como un mapa o un rostro."],"examples":["Leo un libro.","Leo las noticias.","Leo su expresión."],"lemma":"leer","lemmaPos":"verb","synonyms":["descifrar","interpretar","estudiar","comprender"],"number":"singular","gender":"other"}