{"transcript":"ˈelises","exists":true,"definitions":["Dispositivo con palas giratorias que impulsa una aeronave o embarcación.","Cada una de las aspas de un ventilador o molino."],"examples":["Las hélices del avión giraban rápidamente.","El barco avanzaba gracias a sus hélices.","Las hélices del helicóptero creaban una fuerte corriente de aire."],"lemma":"hélice","lemmaPos":"noun","synonyms":["propulsor","aspa","rotor"],"number":"plural","pluralForm":"las hélices","gender":"feminine","source":"hélices"}