{"transcript":"bolˈβeɾ","exists":true,"definitions":["Regresar al lugar de donde se partió.","Girar o dar la vuelta.","Convertirse o transformarse en algo.","Hacer que algo regrese a su estado anterior."],"examples":["Quiero volver a casa.","Volver la página del libro.","Se volvió un experto en la materia.","Volver el agua a su cauce."],"lemma":"volver","lemmaPos":"verb","synonyms":["regresar","retornar","girar","tornar"],"number":"singular","pastTenses":"volví, he vuelto","tense":"present","source":"volver"}