{"transcript":"reˈkwento","exists":true,"definitions":["Acción y efecto de volver a contar algo.","Cómputo o enumeración de cosas o personas.","Narración o relación detallada de un suceso."],"examples":["El recuento de votos fue muy reñido.","Hizo un recuento de los daños tras la tormenta.","Su recuento de la historia fue fascinante."],"lemma":"recuento","lemmaPos":"noun","synonyms":["conteo","cómputo","enumeración","relato","narración"],"number":"singular","pluralForm":"los recuentos","gender":"masculine","source":"recuento"}