{"transcript":"esˈtuβe","exists":true,"definitions":["Primera persona del singular del pretérito perfecto simple de indicativo del verbo estar.","Acción de haber permanecido en un lugar o estado en el pasado.","Haber experimentado o vivido algo en el pasado."],"examples":["Estuve en casa todo el día.","Estuve enfermo la semana pasada.","Estuve pensando en ti.","Estuve de acuerdo con su decisión."],"lemma":"estar","lemmaPos":"verb","synonyms":["fui","permanecí","residí","me encontré"],"number":"singular","tense":"past","pastTenses":"yo estuve (past simple), yo he estado (present perfect)","source":"estuve"}