{"transcript":"la kon.tem.plaˈsjon","exists":true,"definitions":["Acción y efecto de contemplar.","Consideración o meditación profunda sobre algo.","Observación atenta y prolongada de un objeto o fenómeno."],"examples":["La contemplación del paisaje era su pasatiempo favorito.","Se sumergió en la contemplación de la obra de arte.","La contemplación de la naturaleza le trajo paz."],"lemma":"contemplación","lemmaPos":"noun","synonyms":["meditación","observación","reflexión","consideración"],"number":"singular","pluralForm":"las contemplaciones","gender":"feminine","source":"la contemplación"}