{"transcript":"el kanˈdaðo","exists":true,"definitions":["Dispositivo de seguridad que se utiliza para cerrar puertas, verjas, cadenas, etc., y que se abre con una llave o combinación.","Cerradura portátil que se puede colocar en diferentes lugares para asegurar algo."],"examples":["Puso el candado en la bicicleta.","Perdí la llave del candado.","El candado es de acero templado."],"lemma":"candado","lemmaPos":"noun","synonyms":["cerradura","cerrojo","pestillo"],"number":"singular","pluralForm":"los candados","gender":"masculine","source":"el candado"}