{"transcript":"di.βeɾ.si.fi.kaˈsjon","exists":true,"definitions":["Acción y efecto de diversificar.","Variedad de productos o servicios que ofrece una empresa o un sector.","Estrategia para reducir riesgos invirtiendo en diferentes tipos de activos."],"examples":["La diversificación de cultivos es clave.","Buscamos la diversificación de mercados.","La diversificación de la cartera es importante."],"lemma":"diversificación","lemmaPos":"noun","synonyms":["variedad","multiplicación","diferenciación"],"number":"singular","pluralForm":"las diversificaciones","gender":"feminine","source":"diversificación"}