{"transcript":"ˈɡɾado","exists":true,"definitions":["Cada uno de los diversos estados, valores o calidades que puede tener una cosa.","Unidad de medida de la temperatura.","Unidad de medida de ángulos.","Título universitario que se obtiene al terminar una carrera.","Nivel o peldaño en una jerarquía."],"examples":["El agua hierve a cien grados.","Un ángulo de noventa grados.","Obtuvo su grado en medicina.","Un alto grado de responsabilidad."],"lemma":"grado","lemmaPos":"noun","synonyms":["nivel","rango","escalón","título"],"number":"singular","pluralForm":"los grados","gender":"masculine","source":"el grado"}