{"transcript":"enɡloˈβaɾ","exists":true,"definitions":["Incluir o contener varias cosas o elementos dentro de un conjunto o concepto más amplio.","Abarcar, comprender o integrar diferentes partes en un todo."],"examples":["El informe debe englobar todos los aspectos del proyecto.","Su teoría engloba múltiples disciplinas científicas.","Es importante englobar a todos los participantes en la discusión."],"lemma":"englobar","lemmaPos":"verb","synonyms":["incluir","abarcar","comprender","contener","integrar"],"number":"singular","tense":"present","pastTenses":"englobó, ha englobado","source":"englobar"}