{"transcript":"kapuˈtʃon","exists":true,"definitions":["Pieza de plástico o metal que cubre la punta de un bolígrafo o pluma.","Capucha de una prenda de vestir, generalmente puntiaguda.","Cubierta protectora de diversos objetos."],"examples":["Perdí el capuchón del bolígrafo.","Se puso el capuchón para protegerse del frío.","El capuchón de la bujía está suelto."],"lemma":"capuchón","lemmaPos":"noun","synonyms":["capucha","tapa","cubierta","funda"],"number":"singular","pluralForm":"los capuchones","gender":"masculine","source":"capuchón"}