{"transcript":"res.tau̯ˈɾaɾ","source":"restaurar","definitions":["Reparar, renovar o volver a poner algo en el estado o estimación que antes tenía.","Restablecer o recuperar la salud o la fuerza.","Volver a implantar o poner en vigor algo que había sido suprimido o abolido."],"examples":["Restaurar un edificio antiguo.","Restaurar la paz después de un conflicto.","Restaurar la confianza en el equipo."],"lemma":"restaurar","lemmaPos":"verb","synonyms":["reparar","renovar","reconstruir","restablecer","reponer"],"number":"singular","gender":"other"}