{"transcript":"des.mo.neˈti.θes","exists":true,"definitions":["Forma del presente de subjuntivo del verbo desmonetizar, segunda persona del singular (tú).","Forma del presente de subjuntivo del verbo desmonetizar, segunda persona del singular (vos)."],"examples":["Espero que no desmonetices tu canal.","Quizás desmonetices el contenido sin querer.","Si desmonetices esa sección, perderás ingresos."],"lemma":"desmonetizar","lemmaPos":"verb","synonyms":["desvalorizar","devaluar","desactivar monetización"],"number":"singular","pastTenses":"desmonetizaste, has desmonetizado","tense":"present","source":"desmonetices"}