{"transcript":"peɾbeɾˈtiɾ","exists":true,"definitions":["Perturbar el orden o estado de las cosas.","Incitar a alguien a una conducta considerada inmoral o viciosa.","Corromper o alterar el sentido de algo."],"examples":["No dejes que el poder te llegue a pervertir.","Intentaron pervertir el curso de la justicia.","Esa ideología puede pervertir a los jóvenes."],"lemma":"pervertir","lemmaPos":"verb","synonyms":["corromper","viciar","depravar","alterar","envilecer"],"number":"singular","pastTenses":"pervertí, he pervertido","tense":"present","source":"pervertir"}