{"transcript":"pֹ¾oֻˆ־²eֹ¾־²jo","exists":true,"definitions":["Sentencia, adagio o refrֳ¡n.","Dicho de origen popular que expresa una verdad o un consejo."],"examples":["Un proverbio antiguo dice que 'mֳ¡s vale tarde que nunca'.","Los proverbios son parte de la sabidurֳ­a popular.","Cada cultura tiene sus propios proverbios."],"lemma":"proverbio","lemmaPos":"noun","synonyms":["refrֳ¡n","adagio","aforismo","mֳ¡xima"],"number":"singular","pluralForm":"los proverbios","gender":"masculine","source":"proverbio"}