{"transcript":"aˈlambɾe ðe ˈpuas","exists":true,"definitions":["Tipo de alambre con puntas afiladas o púas a intervalos regulares, utilizado comúnmente para cercas.","Cerca hecha con este tipo de alambre."],"examples":["El rancho estaba rodeado por alambre de púas.","Tuvimos que cortar el alambre de púas para pasar.","El prisionero intentó escalar el alambre de púas."],"lemma":"alambre de púas","lemmaPos":"noun","synonyms":["alambrada de púas","cerca de púas"],"number":"singular","pluralForm":"los alambres de púas","gender":"masculine","source":"alambre de púas"}