{"transcript":"ri.xiˈðeθ","exists":true,"definitions":["Falta de flexibilidad o de capacidad para doblarse.","Dureza o firmeza de un cuerpo.","Severidad o inflexibilidad en el carácter o en las normas."],"examples":["La rigidez del material lo hace muy resistente.","Sufre de rigidez en las articulaciones.","La rigidez de sus principios era admirable."],"lemma":"rigidez","lemmaPos":"noun","synonyms":["inflexibilidad","dureza","tiesura","severidad"],"number":"singular","pluralForm":"las rigideces","gender":"feminine","source":"rigidez"}