{"transcript":"koˈbɾamos","exists":true,"definitions":["Nosotros recibimos dinero por un servicio o producto.","Nosotros tenemos que pagar una deuda o impuesto.","Nosotros adquirimos o ganamos algo (como fuerza o ánimo)."],"examples":["Nosotros cobramos el cheque hoy.","Siempre cobramos por adelantado.","Nosotros cobramos fuerzas después del descanso."],"lemma":"cobrar","lemmaPos":"verb","synonyms":["recibir","recaudar","percibir","exigir"],"number":"plural","tense":"present","pastTenses":"cobramos (past simple), hemos cobrado (present perfect)","source":"cobramos"}