{"source":"secretaria","number":"singular","lemma":"secretaria","lemmaPos":"noun","definitions":["Persona que se encarga de la correspondencia, la agenda, los documentos y otras tareas administrativas en una oficina, empresa o para una persona.","Mujer que trabaja en una oficina, empresa o para una persona, realizando tareas administrativas y de apoyo.","En algunos países, cargo político de alto nivel, equivalente a ministro o subsecretario."],"examples":["La secretaria organizó la reunión.","Necesito hablar con la secretaria del director.","La secretaria tomó notas durante la junta.","Mi secretaria es muy eficiente.","Ella trabaja como secretaria ejecutiva."],"synonyms":["asistente","auxiliar","administrativa"],"transcript":"se.kɾeˈta.ɾja","gender":"feminine"}