{"transcript":"saˈβɾa","exists":true,"definitions":["Tendrá conocimiento o información sobre algo en el futuro.","Poseerá la habilidad o capacidad para realizar una acción más adelante.","Expresa probabilidad o conjetura sobre un conocimiento en el presente."],"examples":["Él sabrá la verdad mañana.","¿Quién sabrá dónde están las llaves?","Ella sabrá resolver el problema."],"lemma":"saber","lemmaPos":"verb","synonyms":["conocerá","comprenderá","entenderá","averiguará"],"number":"singular","pastTenses":"supo, ha sabido","tense":"future","source":"sabrá"}