{"transcript":"fundiˈθjon","exists":true,"definitions":["Acción y efecto de fundir metales u otros cuerpos sólidos.","Establecimiento donde se funden metales.","Objeto o pieza que ha sido fundida.","Conjunto de moldes para fabricar tipos de imprenta."],"examples":["Trabaja en la fundición de hierro.","La fundición del oro requiere altas temperaturas.","Una pieza de fundición antigua."],"lemma":"fundición","lemmaPos":"noun","synonyms":["fusión","licuación","taller","factoría"],"number":"singular","pluralForm":"las fundiciones","gender":"feminine","source":"fundición"}