{"transcript":"ekskuɾˈsjon","exists":true,"definitions":["Viaje corto a algún sitio como recreo, estudio o ejercicio físico.","Ida a una ciudad, museo o lugar para visitarlo.","Desviación de la fuerza o movimiento de su curso normal."],"examples":["Fuimos de excursión a la montaña.","La excursión escolar fue un éxito.","Mañana salimos de excursión."],"lemma":"excursión","lemmaPos":"noun","synonyms":["viaje","salida","paseo","gira","expedición"],"number":"singular","pluralForm":"las excursiones","gender":"feminine","source":"excursión"}