{"transcript":"tɾanskuˈriɾ","exists":true,"definitions":["Dicho del tiempo, pasar o correr.","Suceder o acontecer algo en el transcurso del tiempo."],"examples":["El tiempo transcurre rápidamente.","Mientras transcurría la reunión, se tomaron decisiones importantes.","Dejar que los días transcurran sin preocupaciones."],"lemma":"transcurrir","lemmaPos":"verb","synonyms":["pasar","correr","suceder","acontecer"],"number":"singular","pastTenses":"transcurrió, ha transcurrido","tense":"present","source":"transcurrir"}