{"exists":true,"definitions":["Tratar de encontrar soluciones o explicaciones innecesariamente complejas a algo sencillo.","Complicar algo que no tiene dificultad.","Tratar de justificar lo injustificable con argumentos falsos."],"examples":["No le busques tres pies al gato, la respuesta es obvia.","Deja de buscarle tres pies al gato y acepta la realidad."],"lemma":"buscar tres pies al gato","lemmaPos":"verb phrase","synonyms":["rizar el rizo","ahogarse en un vaso de agua","buscar la quinta pata al gato"],"number":"singular","gender":"masculine","source":"buscarle tres pies al gato","transcript":""}