{"transcript":"maˈtaɾ","exists":true,"definitions":["Quitar la vida a un ser vivo.","Extinguir o apagar algo, como el fuego o la sed.","Causar gran sufrimiento o molestia a alguien.","Anular o destruir algo."],"examples":["Él va a matar la araña.","Necesito matar la sed con agua fría.","Este calor me va a matar.","Matar el tiempo libre."],"lemma":"matar","lemmaPos":"verb","synonyms":["asesinar","ejecutar","eliminar","extinguir","aniquilar"],"number":"singular","pastTenses":"mató, ha matado","tense":"present","source":"matar"}