{"transcript":"aˈoras","exists":true,"definitions":["Forma conjugada del verbo ahorrar en la segunda persona del singular (tú) del presente de indicativo.","Guardar dinero u otros bienes para el futuro.","Evitar un gasto o consumo."],"examples":["Si ahorras ahora, podrás viajar después.","¿Cuánto ahorras al mes?","Con esa medida, ahorras tiempo y esfuerzo."],"lemma":"ahorrar","lemmaPos":"verb","synonyms":["guardar","economizar","reservar","atesorar"],"number":"singular","pastTenses":"ahorraste, has ahorrado","tense":"present","source":"ahorras"}