{"transcript":"a.sisˈtiɾ","exists":true,"definitions":["Estar presente en un lugar o en un acto.","Prestar ayuda o asistencia a alguien.","Cuidar o atender a una persona, especialmente a un enfermo."],"examples":["Voy a asistir a la conferencia.","El médico asistió al paciente.","Ella asiste a su abuela todos los días."],"lemma":"asistir","lemmaPos":"verb","synonyms":["ayudar","socorrer","concurrir","presentarse"],"number":"singular","pastTenses":"asistí, has asistido","tense":"present","source":"asistir"}