{"transcript":"fiˈɡuɾa","exists":true,"definitions":["Forma exterior de un cuerpo.","Estatua o pintura que representa el cuerpo de un hombre o animal.","Persona que destaca en una actividad determinada.","Símbolo o representación de algo."],"examples":["Tiene una figura esbelta.","Es una figura del cine.","Dibuja una figura geométrica."],"lemma":"figura","lemmaPos":"noun","synonyms":["forma","silueta","personaje","imagen","talla"],"number":"singular","pluralForm":"las figuras","gender":"feminine","source":"figura"}