{"transcript":"ekspeɾimenˈtando","exists":true,"definitions":["Sintiendo una sensación, emoción o estado.","Realizando pruebas o experimentos para comprobar algo.","Conociendo algo por propia experiencia."],"examples":["Estamos experimentando cambios.","Sigue experimentando en el laboratorio.","Está experimentando mucha alegría."],"lemma":"experimentar","lemmaPos":"verb","synonyms":["probando","ensayando","sintiendo","vivenciando"],"number":"singular","pastTenses":"experimenté, he experimentado","tense":"present","source":"experimentando"}