{"transcript":"po.seˈi.ða","exists":true,"definitions":["Que ha sido poseída o tomada por algo o alguien.","Que está bajo el control o influencia de un espíritu o entidad.","Que se tiene en propiedad o posesión."],"examples":["La casa parecía poseída por una energía extraña.","Se sentía poseída por una fuerza incontrolable.","La tierra fue poseída por sus ancestros."],"lemma":"poseer","lemmaPos":"verb","synonyms":["dominada","ocupada","controlada","tenida"],"number":"singular","pastTenses":"poseyó, ha poseído","tense":"past","gender":"feminine","source":"poseída"}