{"transcript":"manˈtjene","exists":true,"definitions":["Acción de conservar algo en su ser o estado.","Acción de sustentar o alimentar.","Acción de defender una opinión o idea.","Acción de continuar haciendo algo."],"examples":["Él mantiene la casa limpia.","Ella mantiene a su familia.","El equipo mantiene la esperanza.","La empresa mantiene su compromiso."],"lemma":"mantener","lemmaPos":"verb","synonyms":["conservar","sostener","preservar","soportar"],"number":"singular","pastTenses":"mantuvo, ha mantenido","tense":"present","source":"mantiene"}