{"transcript":"arasˈtɾando","exists":true,"definitions":["Llevando a alguien o algo por el suelo tirando de ello","Moviéndose rozando el cuerpo con la tierra","Llevando a alguien a algo malo o difícil de forma inevitable"],"examples":["Está arrastrando la silla","Viene arrastrando los pies","Me está arrastrando a sus problemas"],"lemma":"arrastrar","lemmaPos":"verb","synonyms":["remolcando","tirando","rastreando","jalando"],"number":"singular","pastTenses":"había arrastrado, hube arrastrado, arrastré","tense":"present","source":"arrastrando"}