{"transcript":"meˈðjana","exists":true,"definitions":["Segmento que une un vértice de un triángulo con el punto medio del lado opuesto.","Valor que ocupa el lugar central de todos los datos cuando estos están ordenados.","Muro o zona divisoria entre los dos sentidos de circulación de una carretera."],"examples":["Calcula la mediana del triángulo.","La mediana estadística es cinco.","El coche chocó contra la mediana."],"lemma":"mediana","lemmaPos":"noun","synonyms":["valor central","isleta","berma"],"number":"singular","pluralForm":"las medianas","gender":"feminine","source":"mediana"}