{"transcript":"e.fekˈti.βo","exists":true,"definitions":["Que produce el efecto esperado, que es eficaz.","Real y verdadero, en oposición a lo que es teórico o imaginario.","Dicho de dinero, en metálico o en billetes y monedas."],"examples":["Es un método muy efectivo para aprender.","La medida fue efectiva de inmediato.","El pago se realizó en efectivo."],"lemma":"efectivo","lemmaPos":"adjective","synonyms":["eficaz","válido","real","verdadero","líquido"],"number":"singular","gender":"masculine","source":"efectivo"}