{"transcript":"ra.ðjaˈθjon","exists":true,"definitions":["Acción y efecto de irradiar.","Energía ondulatoria o partículas materiales que se propagan a través del espacio.","Conjunto de los rayos emitidos por un cuerpo radiante."],"examples":["La radiación solar es intensa.","Niveles altos de radiación ultravioleta.","Protección contra la radiación nuclear."],"lemma":"radiación","lemmaPos":"noun","synonyms":["irradiación","emisión","propagación","fulgor"],"number":"singular","pluralForm":"las radiaciones","gender":"feminine","source":"radiación"}