{"transcript":"pestaˈɲita","exists":true,"definitions":["Diminutivo de pestaña.","Pelo corto que nace en el borde del párpado.","Pequeña pieza o saliente en el borde de algo para sujetarlo o encajarlo.","En informática, pequeña lengüeta en una interfaz gráfica."],"examples":["La niña tiene una pestañita en la mejilla.","Haz clic en la pestañita del navegador.","Dobla la pestañita de papel."],"lemma":"pestaña","lemmaPos":"noun","synonyms":["lengüeta","reborde","saliente"],"number":"singular","pluralForm":"las pestañitas","gender":"feminine","source":"pestañita"}