{"transcript":"saŋˈɡɾona","exists":true,"definitions":["Persona que se queja mucho o es fastidiosa.","Persona engreída o creída.","Persona que actúa de manera desagradable o antipática."],"examples":["Siempre está de sangrona con sus quejas.","Se puso muy sangrona después de ganar el premio.","Su actitud sangrona molesta a todos."],"lemma":"sangrón","lemmaPos":"adjective","synonyms":["quejumbroso","fastidioso","engreído","creído","antipático"],"number":"singular","gender":"feminine","source":"sangrona"}